cursofiapml/__init__.py
cursofiapml/core.py
cursofiapml_package-1.0.0.dist-info/METADATA
cursofiapml_package-1.0.0.dist-info/WHEEL
cursofiapml_package-1.0.0.dist-info/top_level.txt
cursofiapml_package-1.0.0.dist-info/RECORD
